kaptik/__init__.py
kaptik/api.py
kaptik/pytorch.py
kaptik/utils.py
kaptik-0.0.1.dist-info/LICENSE
kaptik-0.0.1.dist-info/METADATA
kaptik-0.0.1.dist-info/WHEEL
kaptik-0.0.1.dist-info/top_level.txt
kaptik-0.0.1.dist-info/RECORD
