Metadata-Version: 2.1
Name: kaptik
Version: 0.0.1
Summary: Datastreaming Client
Author-email: Corey Hu <contact@coreyhu.com>
Project-URL: homepage, https://github.com/coreyhu/kaptik
Project-URL: repository, https://github.com/coreyhu/kaptik
Classifier: Programming Language :: Python :: 3
Classifier: License :: OSI Approved :: GNU General Public License v3 (GPLv3)
Classifier: Operating System :: OS Independent
Classifier: Intended Audience :: Developers
Requires-Python: >=3.7
License-File: LICENSE
Requires-Dist: pyarrow (>=11.0.0)
Requires-Dist: python-dotenv (>=0.21.1)
Requires-Dist: msgpack (>=1.0.4)
Provides-Extra: dev
Requires-Dist: torch (>=1.13.1) ; extra == 'dev'
Requires-Dist: datasets (>=2.9.0) ; extra == 'dev'
Requires-Dist: pre-commit (>=3.0.0) ; extra == 'dev'
Requires-Dist: yapf (>=0.32.0) ; extra == 'dev'
Requires-Dist: jupyterlab (>=3.6.1) ; extra == 'dev'
